cryptomarket/__init__.py
cryptomarket/args.py
cryptomarket/client.py
cryptomarket/exceptions.py
cryptomarket/hmac_auth.py
cryptomarket/http_client.py
cryptomarket/dataclasses/CommitRisk.py
cryptomarket/dataclasses/__init__.py
cryptomarket/dataclasses/aclSettings.py
cryptomarket/dataclasses/address.py
cryptomarket/dataclasses/amountLock.py
cryptomarket/dataclasses/balance.py
cryptomarket/dataclasses/candle.py
cryptomarket/dataclasses/commission.py
cryptomarket/dataclasses/convertedCandles.py
cryptomarket/dataclasses/convertedCandlesOfSymbol.py
cryptomarket/dataclasses/currency.py
cryptomarket/dataclasses/fee.py
cryptomarket/dataclasses/metaTransaction.py
cryptomarket/dataclasses/nativeTransaction.py
cryptomarket/dataclasses/network.py
cryptomarket/dataclasses/order.py
cryptomarket/dataclasses/orderBook.py
cryptomarket/dataclasses/orderBookLevel.py
cryptomarket/dataclasses/price.py
cryptomarket/dataclasses/priceHistory.py
cryptomarket/dataclasses/pricePoint.py
cryptomarket/dataclasses/publicTrade.py
cryptomarket/dataclasses/report.py
cryptomarket/dataclasses/subAccount.py
cryptomarket/dataclasses/symbol.py
cryptomarket/dataclasses/ticker.py
cryptomarket/dataclasses/trade.py
cryptomarket/dataclasses/tradeOfOrder.py
cryptomarket/dataclasses/transaction.py
cryptomarket/dataclasses/whitelistedAddress.py
cryptomarket/dataclasses/wsCandle.py
cryptomarket/dataclasses/wsMiniTicker.py
cryptomarket/dataclasses/wsOrderBook.py
cryptomarket/dataclasses/wsOrderBookTop.py
cryptomarket/dataclasses/wsPriceRate.py
cryptomarket/dataclasses/wsPublicTrade.py
cryptomarket/dataclasses/wsTicker.py
cryptomarket/dataclasses/wsTrade.py
cryptomarket/websockets/__init__.py
cryptomarket/websockets/callback.py
cryptomarket/websockets/callback_cache.py
cryptomarket/websockets/client_auth.py
cryptomarket/websockets/client_base.py
cryptomarket/websockets/interceptors.py
cryptomarket/websockets/manager.py
cryptomarket/websockets/market_data_client.py
cryptomarket/websockets/reusable_callback.py
cryptomarket-3.3.0.dist-info/LICENSE
cryptomarket-3.3.0.dist-info/METADATA
cryptomarket-3.3.0.dist-info/WHEEL
cryptomarket-3.3.0.dist-info/top_level.txt
cryptomarket-3.3.0.dist-info/RECORD
