Metadata-Version: 2.1
Name: cryptomarket
Version: 3.3.0
Summary: Cryptomarket API client library
Home-page: https://github.com/cryptomkt/cryptomkt-python
Author: CryptoMarket
Keywords: api,cryptomkt,cryptomarket,bitcoin,client
Classifier: Intended Audience :: Developers
Classifier: Programming Language :: Python :: 3
Classifier: Programming Language :: Python :: 3.8
Classifier: Programming Language :: Python :: 3.9
Classifier: Programming Language :: Python :: 3.10
Classifier: Programming Language :: Python :: 3.11
Classifier: Programming Language :: Python :: 3.12
Classifier: Programming Language :: Python :: 3 :: Only
Classifier: License :: OSI Approved :: MIT License
Classifier: Operating System :: OS Independent
Classifier: Topic :: Software Development :: Libraries :: Python Modules
Requires-Python: >=3.8
License-File: LICENSE
Requires-Dist: requests ==2.31.0
Requires-Dist: websocket-client ==1.1.0
Requires-Dist: dacite ==1.8.1
Requires-Dist: typing-extensions ==4.9.0
